{"nodes": [{"id": "c_github_ubiverse_prompt_template_md", "label": "prompt-template.md", "file_type": "document", "source_file": "C:\\GitHub\\Ubiverse\\prompt-template.md", "source_location": "L1"}, {"id": "ubiverse_prompt_template_ubiverse_reusable_prompt_template", "label": "Ubiverse Reusable Prompt Template", "file_type": "document", "source_file": "C:\\GitHub\\Ubiverse\\prompt-template.md", "source_location": "L1"}, {"id": "ubiverse_prompt_template_full_prompt_template", "label": "Full prompt template", "file_type": "document", "source_file": "C:\\GitHub\\Ubiverse\\prompt-template.md", "source_location": "L7"}, {"id": "ubiverse_prompt_template_task", "label": "Task", "file_type": "document", "source_file": "C:\\GitHub\\Ubiverse\\prompt-template.md", "source_location": "L13"}, {"id": "ubiverse_prompt_template_goal", "label": "Goal", "file_type": "document", "source_file": "C:\\GitHub\\Ubiverse\\prompt-template.md", "source_location": "L16"}, {"id": "ubiverse_prompt_template_relevant_area", "label": "Relevant area", "file_type": "document", "source_file": "C:\\GitHub\\Ubiverse\\prompt-template.md", "source_location": "L19"}, {"id": "ubiverse_prompt_template_requirements", "label": "Requirements", "file_type": "document", "source_file": "C:\\GitHub\\Ubiverse\\prompt-template.md", "source_location": "L23"}, {"id": "ubiverse_prompt_template_constraints", "label": "Constraints", "file_type": "document", "source_file": "C:\\GitHub\\Ubiverse\\prompt-template.md", "source_location": "L29"}, {"id": "ubiverse_prompt_template_implementation_instructions", "label": "Implementation instructions", "file_type": "document", "source_file": "C:\\GitHub\\Ubiverse\\prompt-template.md", "source_location": "L38"}, {"id": "ubiverse_prompt_template_deliverables", "label": "Deliverables", "file_type": "document", "source_file": "C:\\GitHub\\Ubiverse\\prompt-template.md", "source_location": "L45"}, {"id": "ubiverse_prompt_template_short_prompt_template", "label": "Short prompt template", "file_type": "document", "source_file": "C:\\GitHub\\Ubiverse\\prompt-template.md", "source_location": "L53"}, {"id": "ubiverse_prompt_template_example_prompt", "label": "Example prompt", "file_type": "document", "source_file": "C:\\GitHub\\Ubiverse\\prompt-template.md", "source_location": "L68"}, {"id": "ubiverse_prompt_template_best_results_tips", "label": "Best results tips", "file_type": "document", "source_file": "C:\\GitHub\\Ubiverse\\prompt-template.md", "source_location": "L85"}], "edges": [{"source": "c_github_ubiverse_prompt_template_md", "target": "ubiverse_prompt_template_ubiverse_reusable_prompt_template", "relation": "contains", "confidence": "EXTRACTED", "source_file": "C:\\GitHub\\Ubiverse\\prompt-template.md", "source_location": "L1", "weight": 1.0}, {"source": "ubiverse_prompt_template_ubiverse_reusable_prompt_template", "target": "ubiverse_prompt_template_full_prompt_template", "relation": "contains", "confidence": "EXTRACTED", "source_file": "C:\\GitHub\\Ubiverse\\prompt-template.md", "source_location": "L7", "weight": 1.0}, {"source": "ubiverse_prompt_template_full_prompt_template", "target": "ubiverse_prompt_template_task", "relation": "contains", "confidence": "EXTRACTED", "source_file": "C:\\GitHub\\Ubiverse\\prompt-template.md", "source_location": "L13", "weight": 1.0}, {"source": "ubiverse_prompt_template_full_prompt_template", "target": "ubiverse_prompt_template_goal", "relation": "contains", "confidence": "EXTRACTED", "source_file": "C:\\GitHub\\Ubiverse\\prompt-template.md", "source_location": "L16", "weight": 1.0}, {"source": "ubiverse_prompt_template_full_prompt_template", "target": "ubiverse_prompt_template_relevant_area", "relation": "contains", "confidence": "EXTRACTED", "source_file": "C:\\GitHub\\Ubiverse\\prompt-template.md", "source_location": "L19", "weight": 1.0}, {"source": "ubiverse_prompt_template_full_prompt_template", "target": "ubiverse_prompt_template_requirements", "relation": "contains", "confidence": "EXTRACTED", "source_file": "C:\\GitHub\\Ubiverse\\prompt-template.md", "source_location": "L23", "weight": 1.0}, {"source": "ubiverse_prompt_template_full_prompt_template", "target": "ubiverse_prompt_template_constraints", "relation": "contains", "confidence": "EXTRACTED", "source_file": "C:\\GitHub\\Ubiverse\\prompt-template.md", "source_location": "L29", "weight": 1.0}, {"source": "ubiverse_prompt_template_full_prompt_template", "target": "ubiverse_prompt_template_implementation_instructions", "relation": "contains", "confidence": "EXTRACTED", "source_file": "C:\\GitHub\\Ubiverse\\prompt-template.md", "source_location": "L38", "weight": 1.0}, {"source": "ubiverse_prompt_template_full_prompt_template", "target": "ubiverse_prompt_template_deliverables", "relation": "contains", "confidence": "EXTRACTED", "source_file": "C:\\GitHub\\Ubiverse\\prompt-template.md", "source_location": "L45", "weight": 1.0}, {"source": "ubiverse_prompt_template_ubiverse_reusable_prompt_template", "target": "ubiverse_prompt_template_short_prompt_template", "relation": "contains", "confidence": "EXTRACTED", "source_file": "C:\\GitHub\\Ubiverse\\prompt-template.md", "source_location": "L53", "weight": 1.0}, {"source": "ubiverse_prompt_template_ubiverse_reusable_prompt_template", "target": "ubiverse_prompt_template_example_prompt", "relation": "contains", "confidence": "EXTRACTED", "source_file": "C:\\GitHub\\Ubiverse\\prompt-template.md", "source_location": "L68", "weight": 1.0}, {"source": "ubiverse_prompt_template_ubiverse_reusable_prompt_template", "target": "ubiverse_prompt_template_best_results_tips", "relation": "contains", "confidence": "EXTRACTED", "source_file": "C:\\GitHub\\Ubiverse\\prompt-template.md", "source_location": "L85", "weight": 1.0}], "input_tokens": 0, "output_tokens": 0}